{
    "remotePath": "./",
    "host": "66.225.201.73",
    "username": "airtm",
    "password": "P}QieNM?0x{2",
    "port": 21,
    "secure": false,
    "protocol": "ftp",
    "uploadOnSave": false,
    "passive": false,
    "debug": false,
    "privateKeyPath": null,
    "passphrase": null,
    "agent": null,
    "allow": [],
    "ignore": [
        "\\.vscode",
        "\\.git",
        "\\.DS_Store"
    ],
    "generatedFiles": {
        "extensionsToInclude": [
            ""
        ],
        "path": ""
    }
}